gt4sd/__init__.py
gt4sd/configuration.py
gt4sd/conftest.py
gt4sd/exceptions.py
gt4sd/py.typed
gt4sd/s3.py
gt4sd/algorithms/__init__.py
gt4sd/algorithms/core.py
gt4sd/algorithms/registry.py
gt4sd/algorithms/conditional_generation/__init__.py
gt4sd/algorithms/conditional_generation/guacamol/__init__.py
gt4sd/algorithms/conditional_generation/guacamol/core.py
gt4sd/algorithms/conditional_generation/guacamol/implementation/__init__.py
gt4sd/algorithms/conditional_generation/guacamol/implementation/graph_ga.py
gt4sd/algorithms/conditional_generation/guacamol/implementation/graph_mcts.py
gt4sd/algorithms/conditional_generation/guacamol/implementation/moses_aae.py
gt4sd/algorithms/conditional_generation/guacamol/implementation/moses_organ.py
gt4sd/algorithms/conditional_generation/guacamol/implementation/moses_vae.py
gt4sd/algorithms/conditional_generation/guacamol/implementation/smiles_ga.py
gt4sd/algorithms/conditional_generation/guacamol/implementation/smiles_lstm_hc.py
gt4sd/algorithms/conditional_generation/guacamol/implementation/smiles_lstm_ppo.py
gt4sd/algorithms/conditional_generation/key_bert/__init__.py
gt4sd/algorithms/conditional_generation/key_bert/core.py
gt4sd/algorithms/conditional_generation/key_bert/implementation.py
gt4sd/algorithms/conditional_generation/molgx/__init__.py
gt4sd/algorithms/conditional_generation/molgx/core.py
gt4sd/algorithms/conditional_generation/molgx/implementation.py
gt4sd/algorithms/conditional_generation/paccmann_rl/__init__.py
gt4sd/algorithms/conditional_generation/paccmann_rl/core.py
gt4sd/algorithms/conditional_generation/paccmann_rl/implementation.py
gt4sd/algorithms/conditional_generation/regression_transformer/__init__.py
gt4sd/algorithms/conditional_generation/regression_transformer/core.py
gt4sd/algorithms/conditional_generation/regression_transformer/implementation.py
gt4sd/algorithms/conditional_generation/regression_transformer/utils.py
gt4sd/algorithms/conditional_generation/reinvent/__init__.py
gt4sd-1.5.0.dist-info/LICENSE
gt4sd-1.5.0.dist-info/METADATA
gt4sd-1.5.0.dist-info/WHEEL
gt4sd-1.5.0.dist-info/entry_points.txt
gt4sd-1.5.0.dist-info/top_level.txt
gt4sd-1.5.0.dist-info/RECORD
