Metadata-Version: 2.2
Name: gt4sd
Version: 1.5.0
Summary: Generative Toolkit for Scientific Discovery (GT4SD).
Author: GT4SD team
Keywords: GT4SD Generative Models Inference Training
Classifier: Operating System :: OS Independent
Classifier: Programming Language :: Python :: 3
Classifier: Programming Language :: Python :: 3.7
Classifier: Programming Language :: Python :: 3.8
License-File: LICENSE
Requires-Dist: accelerate
Requires-Dist: datasets
Requires-Dist: diffusers
Requires-Dist: enzeptional
Requires-Dist: importlib_metadata
Requires-Dist: importlib_resources
Requires-Dist: ipaddress
Requires-Dist: joblib
Requires-Dist: gt4sd-molformer
Requires-Dist: gt4sd-trainer-hf-pl
Requires-Dist: keras
Requires-Dist: keybert
Requires-Dist: minio
Requires-Dist: modlamp
Requires-Dist: molecule_generation
Requires-Dist: molgx
Requires-Dist: nglview
Requires-Dist: numpy
Requires-Dist: pytorch_lightning
Requires-Dist: pyarrow
Requires-Dist: pydantic
Requires-Dist: pymatgen
Requires-Dist: pyTDC!=0.3.8
Requires-Dist: pyyaml
Requires-Dist: rdkit
Requires-Dist: regex
Requires-Dist: reinvent-chemistry
Requires-Dist: sacremoses
Requires-Dist: scikit-learn
Requires-Dist: scikit-optimize
Requires-Dist: scipy
Requires-Dist: sentencepiece
Requires-Dist: sympy
Requires-Dist: tables
Requires-Dist: tape-proteins
Requires-Dist: tensorboard
Requires-Dist: tensorflow
Requires-Dist: torch
Requires-Dist: torchdrug
Requires-Dist: torchmetrics
Requires-Dist: torchvision
Requires-Dist: transformers<4.26.0
Requires-Dist: typing_extensions
Requires-Dist: wheel
Requires-Dist: xgboost
Provides-Extra: extras
Requires-Dist: cogmol-inference; extra == "extras"
